kats/__init__.py
kats/compat/__init__.py
kats/compat/compat.py
kats/compat/pandas.py
kats/compat/sklearn.py
kats/compat/statsmodels.py
kats/consts.py
kats/data/README
kats/data/__init__.py
kats/data/air_passengers.csv
kats/data/mean_change_detection_test.csv
kats/data/multi_ts.csv
kats/data/multivariate_anomaly_simulated_data.csv
kats/data/peyton_manning.csv
kats/data/retail_sales.csv
kats/data/utils.py
kats/data/yosemite_temps.csv
kats/detectors/__init__.py
kats/detectors/cusum_detection.py
kats/detectors/cusum_model.py
kats/detectors/detector.py
kats/detectors/detector_consts.py
kats/detectors/dtwcpd.py
kats/detectors/hourly_ratio_detection.py
kats/detectors/interval_detector.py
kats/detectors/meta_learning/__init__.py
kats/detectors/meta_learning/exceptions.py
kats/detectors/meta_learning/hpt_tuning.py
kats/detectors/meta_learning/metalearning_detection_model.py
kats/detectors/meta_learning/synth_metadata_reader.py
kats/detectors/multivariate_detector.py
kats/detectors/outlier.py
kats/detectors/outlier_detector.py
kats/detectors/residual_translation.py
kats/detectors/robust_stat_detection.py
kats/detectors/seasonality.py
kats/detectors/stat_sig_detector.py
kats/detectors/trend_mk.py
kats/metrics/__init__.py
kats/metrics/metadata.py
kats/metrics/metrics.py
kats/models/__init__.py
kats/models/arima.py
kats/models/bayesian_var.py
kats/models/ensemble/__init__.py
kats/models/ensemble/ensemble.py
kats/models/ensemble/kats_ensemble.py
kats/models/ensemble/median_ensemble.py
kats/models/ensemble/weighted_avg_ensemble.py
kats/models/harmonic_regression.py
kats/models/holtwinters.py
kats/models/linear_model.py
kats/models/lstm.py
kats/models/metalearner/__init__.py
kats/models/metalearner/metalearner_hpt.py
kats/models/metalearner/metalearner_modelselect.py
kats/models/metalearner/metalearner_predictability.py
kats/models/model.py
kats/models/nowcasting/__init__.py
kats/models/nowcasting/dynamic_nowcasting.py
kats/models/nowcasting/feature_extraction.py
tinykats_corestack-0.2.1.dist-info/LICENSE
tinykats_corestack-0.2.1.dist-info/WHEEL
tinykats_corestack-0.2.1.dist-info/METADATA
tinykats_corestack-0.2.1.dist-info/RECORD
