Metadata-Version: 2.1
Name: tinykats-corestack
Version: 0.2.1
Summary: Stripped down version of Kats (facebookresearch/Kats)
Home-page: https://github.com/corestacklabs/tinykats_corestack
Keywords: timeseries,forecast
Author: Hem Chandra Padhalni
Author-email: hem.chandra@corestack.io
Maintainer: Hem Chandra Padhalni
Maintainer-email: hem.chandra@corestack.io
Requires-Python: >=3.8,<3.10
Classifier: Programming Language :: Python :: 3
Classifier: Programming Language :: Python :: 3.8
Classifier: Programming Language :: Python :: 3.9
Provides-Extra: pytorch
Requires-Dist: matplotlib (==3.6.0)
Requires-Dist: numba (==0.56.3)
Requires-Dist: numpy (==1.21.0)
Requires-Dist: packaging (==21.3)
Requires-Dist: pandas (==1.3.5)
Requires-Dist: python-dateutil (==2.8.0)
Requires-Dist: scikit-learn (==1.1.2)
Requires-Dist: scipy (==1.7.3)
Requires-Dist: seaborn (==0.11.1)
Requires-Dist: statsmodels (==0.12.2)
Requires-Dist: torch (==1.12.1); extra == "pytorch"
Project-URL: Repository, https://github.com/corestacklabs/tinykats_corestack
